twodlearn/Autoencoder.py
twodlearn/DBM.py
twodlearn/GMM.py
twodlearn/__init__.py
twodlearn/base.py
twodlearn/common.py
twodlearn/constrained.py
twodlearn/convnet.py
twodlearn/debug.py
twodlearn/dense.py
twodlearn/feedforward.py
twodlearn/kernels.py
twodlearn/linalg.py
twodlearn/losses.py
twodlearn/monitoring.py
twodlearn/normalizer.py
twodlearn/optim.py
twodlearn/optimv2.py
twodlearn/parallel.py
twodlearn/recurrent.py
twodlearn/stacked.py
twodlearn/unsupervised.py
twodlearn/bayesnet/__init__.py
twodlearn/bayesnet/bayesnet.py
twodlearn/bayesnet/distributions.py
twodlearn/bayesnet/gaussian_process.py
twodlearn/bayesnet/linear.py
twodlearn/bayesnet/losses.py
twodlearn/bayesnet/recurrent.py
twodlearn/core/__init__.py
twodlearn/core/array.py
twodlearn/core/autoinit.py
twodlearn/core/common.py
twodlearn/core/context.py
twodlearn/core/exceptions.py
twodlearn/core/initializers.py
twodlearn/core/layers.py
twodlearn/core/options.py
twodlearn/core/save.py
twodlearn/core/search.py
twodlearn/core/shortcuts.py
twodlearn/core/variable.py
twodlearn/core/ops/__init__.py
twodlearn/datasets/Batch_generator.py
twodlearn/datasets/LargeMovieReview.py
twodlearn/datasets/__init__.py
twodlearn/datasets/base.py
twodlearn/datasets/cifar10.py
twodlearn/datasets/cyber.py
twodlearn/datasets/mnist.py
twodlearn/datasets/tsdataset.py
twodlearn/datasets/unbalanced.py
twodlearn/datasets/vocabulary_stem_coding.py
twodlearn/reinforce/__init__.py
twodlearn/reinforce/systems.py
twodlearn/reinforce/modelica/__init__.py
twodlearn/reinforce/modelica/modelica_env.py
twodlearn/reinforce/modelica/modelica_model.py
twodlearn/reinforce/modelica/controllers/__init__.py
twodlearn/reinforce/modelica/controllers/noisy_fo/__init__.py
twodlearn/reinforce/modelica/controllers/saturated_noisy_fo/__init__.py
twodlearn/reinforce/modelica/models/__init__.py
twodlearn/reinforce/modelica/models/combined_cycle/__init__.py
twodlearn-0.5.0.dist-info/DESCRIPTION.rst
twodlearn-0.5.0.dist-info/METADATA
twodlearn-0.5.0.dist-info/RECORD
twodlearn-0.5.0.dist-info/WHEEL
twodlearn-0.5.0.dist-info/metadata.json
twodlearn-0.5.0.dist-info/top_level.txt
