Metadata-Version: 2.0
Name: twodlearn
Version: 0.5.0
Summary: Easy development of machine learning models
Home-page: https://github.com/danmar3/twodlearn
Author: Daniel L. Marino
Author-email: marinodl@vcu.edu
License: Apache 2.0
Platform: UNKNOWN
Requires-Python: >=3.5.2
Provides-Extra: development
Provides-Extra: reinforce
Requires-Dist: matplotlib
Requires-Dist: pandas
Requires-Dist: pathlib
Requires-Dist: tensorflow
Requires-Dist: tensorflow-datasets
Requires-Dist: tensorflow-probability
Requires-Dist: tqdm
Requires-Dist: xarray
Provides-Extra: development
Requires-Dist: jupyter; extra == 'development'
Requires-Dist: line-profiler; extra == 'development'
Requires-Dist: pytest; extra == 'development'
Requires-Dist: pytest-faulthandler; extra == 'development'
Provides-Extra: reinforce
Requires-Dist: casadi; extra == 'reinforce'
Requires-Dist: gym; extra == 'reinforce'
Requires-Dist: pybullet (==2.4.5); extra == 'reinforce'
